app/bot_start.py
telegram_crypto_price_bot/__init__.py
telegram_crypto_price_bot/_version.py
telegram_crypto_price_bot/price_bot.py
telegram_crypto_price_bot/bot/__init__.py
telegram_crypto_price_bot/bot/bot_base.py
telegram_crypto_price_bot/bot/bot_config.py
telegram_crypto_price_bot/bot/bot_config_types.py
telegram_crypto_price_bot/bot/bot_handlers_config.py
telegram_crypto_price_bot/bot/bot_handlers_config_typing.py
telegram_crypto_price_bot/chart_info/__init__.py
telegram_crypto_price_bot/chart_info/chart_info.py
telegram_crypto_price_bot/chart_info/chart_info_file_saver.py
telegram_crypto_price_bot/coin_info/__init__.py
telegram_crypto_price_bot/coin_info/coin_info_job.py
telegram_crypto_price_bot/coin_info/coin_info_scheduler.py
telegram_crypto_price_bot/coingecko/__init__.py
telegram_crypto_price_bot/coingecko/coingecko_price_api.py
telegram_crypto_price_bot/command/__init__.py
telegram_crypto_price_bot/command/command_base.py
telegram_crypto_price_bot/command/command_data.py
telegram_crypto_price_bot/command/command_dispatcher.py
telegram_crypto_price_bot/command/commands.py
telegram_crypto_price_bot/config/__init__.py
telegram_crypto_price_bot/config/config_file_sections_loader.py
telegram_crypto_price_bot/config/config_loader_ex.py
telegram_crypto_price_bot/config/config_object.py
telegram_crypto_price_bot/config/config_section_loader.py
telegram_crypto_price_bot/config/config_sections_loader.py
telegram_crypto_price_bot/config/config_typing.py
telegram_crypto_price_bot/info_message_sender/__init__.py
telegram_crypto_price_bot/info_message_sender/chart_info_message_sender.py
telegram_crypto_price_bot/info_message_sender/chart_price_info_message_sender.py
telegram_crypto_price_bot/info_message_sender/coin_info_message_sender.py
telegram_crypto_price_bot/info_message_sender/info_message_sender_base.py
telegram_crypto_price_bot/info_message_sender/price_info_message_sender.py
telegram_crypto_price_bot/lang/lang_en.xml
telegram_crypto_price_bot-0.5.2.dist-info/licenses/LICENSE
telegram_crypto_price_bot-0.5.2.dist-info/METADATA
telegram_crypto_price_bot-0.5.2.dist-info/WHEEL
telegram_crypto_price_bot-0.5.2.dist-info/top_level.txt
telegram_crypto_price_bot-0.5.2.dist-info/RECORD
